etlt_mysql/__init__.py
etlt_mysql/writer/MySqlLoaderWriter.py
etlt_mysql/writer/__init__.py
etlt_mysql-1.0.0.dist-info/LICENSE
etlt_mysql-1.0.0.dist-info/METADATA
etlt_mysql-1.0.0.dist-info/WHEEL
etlt_mysql-1.0.0.dist-info/RECORD
