Metadata-Version: 2.1
Name: ETLT-MySQL
Version: 1.0.0
Summary: ETLT extension for MariaDB and MySQL databases
Home-page: https://github.com/PyETLT/etlt
License: MIT
Keywords: ETLT,MySQL,MariaDB
Author: Set Based IT Consultancy
Author-email: info@setbased.nl
Requires-Python: >=3.9.0,<4.0.0
Classifier: Development Status :: 5 - Production/Stable
Classifier: Environment :: Console
Classifier: Intended Audience :: Developers
Classifier: License :: OSI Approved :: MIT License
Classifier: Operating System :: OS Independent
Classifier: Programming Language :: Python :: 3
Classifier: Programming Language :: Python :: 3.9
Classifier: Programming Language :: Python :: 3.10
Classifier: Programming Language :: Python :: 3.11
Classifier: Programming Language :: Python :: 3.12
Classifier: Topic :: Database
Requires-Dist: ETLT (>=1.0.0,<2.0.0)
Requires-Dist: pytz (>=2020.1,<2021.0)
Project-URL: Repository, https://github.com/PyETLT/etlt
